{
    "standard": {
        "default": [
            {
                "boards": ["brd4338a", "brd2605a"],
                "arguments": [""]
            },
            {
                "boards": ["brd4338a"],
                "arguments": ["--output_suffix copy-sources", "--copy-sources"]
            }
        ],
        "platform_template": [
            {
                "boards": ["brd4338a"],
                "arguments": ["--output_suffix  peripherals-icd","--with_app matter_peripherals_917soc,matter_icd_core"]
            }
        ],
        "lighting_app": [
            {
                "boards": ["brd4338a"],
                "arguments": ["--output_suffix matter_aws_transport_lwip", "--with_app matter_aws,matter_aws_transport_lwip"]
            }
        ]
    },
    "full": {
        "default": [
            {
                "boards": ["brd4343s"],
                "arguments": [""]
            },
            {
                "boards": ["brd4343s"],
                "arguments": ["--output_suffix copy-sources", "--copy-sources"]
            }
        ]
    }
}